gitbook_dl/__init__.py
gitbook_dl/converter.py
gitbook_dl-0.2.0.dist-info/LICENSE
gitbook_dl-0.2.0.dist-info/WHEEL
gitbook_dl-0.2.0.dist-info/METADATA
gitbook_dl-0.2.0.dist-info/RECORD
