Metadata-Version: 2.1
Name: gitbook-dl
Version: 0.2.0
Summary: gitbook-dl
Home-page: https://github.com/alwinw/gitbook-dl
License: MIT
Author: alwinw
Author-email: 16846521+alwinw@users.noreply.github.com
Requires-Python: >=3.7,<4.0
Classifier: License :: OSI Approved :: MIT License
Classifier: Programming Language :: Python :: 3
Classifier: Programming Language :: Python :: 3.10
Classifier: Programming Language :: Python :: 3.7
Classifier: Programming Language :: Python :: 3.8
Classifier: Programming Language :: Python :: 3.9
Requires-Dist: pypandoc (>=1.8.1,<2.0.0)
Project-URL: Documentation, https://github.com/alwinw/gitbook-dl
Project-URL: Repository, https://github.com/alwinw/gitbook-dl
